st_ant_carousel/__init__.py
st_ant_carousel/frontend/build/asset-manifest.json
st_ant_carousel/frontend/build/bootstrap.min.css
st_ant_carousel/frontend/build/index.html
st_ant_carousel/frontend/build/precache-manifest.2607c490f9520a6a70a96334da952fb8.js
st_ant_carousel/frontend/build/precache-manifest.9989d6d569cd7fb09a9be32953a8bb99.js
st_ant_carousel/frontend/build/service-worker.js
st_ant_carousel/frontend/build/static/js/2.6435dd4a.chunk.js
st_ant_carousel/frontend/build/static/js/2.6435dd4a.chunk.js.LICENSE.txt
st_ant_carousel/frontend/build/static/js/2.6435dd4a.chunk.js.map
st_ant_carousel/frontend/build/static/js/2.6c1beff1.chunk.js
st_ant_carousel/frontend/build/static/js/2.6c1beff1.chunk.js.LICENSE.txt
st_ant_carousel/frontend/build/static/js/2.6c1beff1.chunk.js.map
st_ant_carousel/frontend/build/static/js/main.6acda223.chunk.js
st_ant_carousel/frontend/build/static/js/main.6acda223.chunk.js.map
st_ant_carousel/frontend/build/static/js/main.a2df1366.chunk.js
st_ant_carousel/frontend/build/static/js/main.a2df1366.chunk.js.map
st_ant_carousel/frontend/build/static/js/runtime-main.502c8693.js
st_ant_carousel/frontend/build/static/js/runtime-main.502c8693.js.map
st_ant_carousel-0.0.3.dist-info/LICENSE
st_ant_carousel-0.0.3.dist-info/METADATA
st_ant_carousel-0.0.3.dist-info/WHEEL
st_ant_carousel-0.0.3.dist-info/top_level.txt
st_ant_carousel-0.0.3.dist-info/RECORD
