Metadata-Version: 2.1
Name: st-ant-carousel
Version: 0.0.3
Summary: Streamlit Component for ANT Carousel
Author: 
Author-email: 
Requires-Python: >=3.6
License-File: LICENSE
Requires-Dist: streamlit (>=0.63)
